fastapi_oauth20-0.0.1.dist-info/METADATA
fastapi_oauth20-0.0.1.dist-info/WHEEL
fastapi_oauth20-0.0.1.dist-info/entry_points.txt
fastapi_oauth20-0.0.1.dist-info/licenses/LICENSE
fastapi_oauth20/__init__.py
fastapi_oauth20/clients/__init__.py
fastapi_oauth20/clients/feishu.py
fastapi_oauth20/clients/gitee.py
fastapi_oauth20/clients/github.py
fastapi_oauth20/clients/google.py
fastapi_oauth20/clients/linuxdo.py
fastapi_oauth20/clients/oschina.py
fastapi_oauth20/errors.py
fastapi_oauth20/integrations/__init__.py
fastapi_oauth20/integrations/fastapi.py
fastapi_oauth20/oauth20.py
fastapi_oauth20/py.typed
fastapi_oauth20-0.0.1.dist-info/RECORD
