Metadata-Version: 2.1
Name: fastapi-oauth20
Version: 0.0.1
Summary: 在 FastAPI 中异步授权 OAuth 2.0 客户端
Author-Email: Wu Clan <jianhengwu0407@gmail.com>
License: MIT
Classifier: Intended Audience :: Developers
Classifier: License :: OSI Approved :: MIT License
Classifier: Programming Language :: Python :: 3 :: Only
Classifier: Programming Language :: Python :: 3.10
Classifier: Programming Language :: Python :: 3.11
Classifier: Programming Language :: Python :: 3.12
Classifier: Programming Language :: Python :: 3.13
Classifier: Topic :: Software Development :: Libraries
Classifier: Topic :: Software Development :: Libraries :: Python Modules
Project-URL: homepage, https://github.com/fastapi-practices/fastapi_oauth20
Project-URL: repository, https://github.com/fastapi-practices/fastapi_oauth20
Requires-Python: >=3.10
Requires-Dist: httpx>=0.18.0
